README.md
setup.cfg
setup.py
distributions/Binomialdistribution.py
distributions/Gaussiandistribution.py
distributions/Generaldistribution.py
distributions/__init__.py
udacity_joseph_distributions.egg-info/PKG-INFO
udacity_joseph_distributions.egg-info/SOURCES.txt
udacity_joseph_distributions.egg-info/dependency_links.txt
udacity_joseph_distributions.egg-info/not-zip-safe
udacity_joseph_distributions.egg-info/top_level.txt