Metadata-Version: 1.0
Name: udacity-joseph-distributions
Version: 0.1
Summary: Gaussian distributions
Home-page: UNKNOWN
Author: Joseph Cheng
Author-email: joseph.wc.cheng@gmail.com
License: UNKNOWN
Platform: UNKNOWN
